linear_reg/__init__.py
linear_reg/main.py
linear_reg/simple_linear_regr.py
linear_reg/simple_linear_regr_utils.py
simplelinearregress-0.0.1.dist-info/LICENSE
simplelinearregress-0.0.1.dist-info/METADATA
simplelinearregress-0.0.1.dist-info/WHEEL
simplelinearregress-0.0.1.dist-info/top_level.txt
simplelinearregress-0.0.1.dist-info/RECORD
