Metadata-Version: 2.1
Name: simplelinearregress
Version: 0.0.1
Summary: This is a simple implementation of linear regression
Author-email: Cong Kha Nguyen <congkhanguyen@gmail.com>
Project-URL: Homepage, https://github.com/congkhanguyen/simplelinearregress
Project-URL: Bug Tracker, https://github.com/congkhanguyen/simplelinearregress/issues
Classifier: Programming Language :: Python :: 3
Classifier: License :: OSI Approved :: MIT License
Classifier: Operating System :: OS Independent
Requires-Python: >=3.6
License-File: LICENSE
Requires-Dist: numpy
Requires-Dist: scikit-learn
Requires-Dist: matplotlib
Requires-Dist: flask
Requires-Dist: requests
Requires-Dist: python-dotenv
